{
  "db_name": "PostgreSQL",
  "query": "\n            WITH sales AS (\n                SELECT DISTINCT ON (a.nft_id) \n                    a.nft_id, \n                    a.block_time, \n                    a.price \n                FROM activities a\n                WHERE a.tx_type = 'buy'\n                ORDER BY a.nft_id, a.block_time DESC\n            )\n            SELECT \n                n.id, \n                n.name, \n                n.image_url, \n                l.price AS listing_price, \n                s.price AS last_sale, \n                n.owner, \n                l.block_time AS listed_at \n            FROM nfts n\n\t            LEFT JOIN listings l ON l.nft_id = n.id AND l.listed\n\t            LEFT JOIN sales s ON s.nft_id = n.id\n            WHERE n.collection_id = $1 AND n.burned IS NOT NULL AND NOT n.burned\n            ORDER BY l.price\n            LIMIT $2 OFFSET $3\n            ",
  "describe": {
    "columns": [
      {
        "ordinal": 0,
        "name": "id",
        "type_info": "Varchar"
      },
      {
        "ordinal": 1,
        "name": "name",
        "type_info": "Varchar"
      },
      {
        "ordinal": 2,
        "name": "image_url",
        "type_info": "Varchar"
      },
      {
        "ordinal": 3,
        "name": "listing_price",
        "type_info": "Int8"
      },
      {
        "ordinal": 4,
        "name": "last_sale",
        "type_info": "Int8"
      },
      {
        "ordinal": 5,
        "name": "owner",
        "type_info": "Varchar"
      },
      {
        "ordinal": 6,
        "name": "listed_at",
        "type_info": "Timestamptz"
      }
    ],
    "parameters": {
      "Left": [
        "Text",
        "Int8",
        "Int8"
      ]
    },
    "nullable": [
      false,
      true,
      true,
      true,
      true,
      true,
      false
    ]
  },
  "hash": "5de202b00a11d100e805bf72c3a887b83b471c2ee1332951a551c30925f0e20e"
}
