{
  "db_name": "PostgreSQL",
  "query": "\n            SELECT\n                c.id,\n                c.slug, \n                c.supply, \n                c.title, \n                c.description, \n                c.cover_url, \n                c.verified,\n                c.website,\n                c.discord,\n                c.twitter,\n                c.royalty,\n                cs.volumes::BIGINT           AS total_volume,\n                cs.sales::BIGINT             AS total_sale,\n                co.owners::BIGINT            AS total_owner,\n                cl.floor_price::BIGINT       AS floor,\n                cl.listed::BIGINT\n            FROM collections c\n                LEFT JOIN collection_sales cs ON cs.collection_id = c.id\n                LEFT JOIN collection_listings cl ON cl.collection_id = c.id\n                LEFT JOIN collection_owners co ON co.collection_id = c.id\n            WHERE ($1::TEXT IS NULL OR $1::TEXT = '' OR c.id = $1::TEXT)\n                AND ($2::TEXT IS NULL OR $2::TEXT = '' OR c.id IN (\n                    SELECT DISTINCT n.collection_id FROM nfts n\n                    WHERE n.owner = $2\n                ))\n            ORDER BY cs.volumes DESC\n            LIMIT $3 OFFSET $4\n            ",
  "describe": {
    "columns": [
      {
        "ordinal": 0,
        "name": "id",
        "type_info": "Varchar"
      },
      {
        "ordinal": 1,
        "name": "slug",
        "type_info": "Varchar"
      },
      {
        "ordinal": 2,
        "name": "supply",
        "type_info": "Int8"
      },
      {
        "ordinal": 3,
        "name": "title",
        "type_info": "Varchar"
      },
      {
        "ordinal": 4,
        "name": "description",
        "type_info": "Text"
      },
      {
        "ordinal": 5,
        "name": "cover_url",
        "type_info": "Varchar"
      },
      {
        "ordinal": 6,
        "name": "verified",
        "type_info": "Bool"
      },
      {
        "ordinal": 7,
        "name": "website",
        "type_info": "Varchar"
      },
      {
        "ordinal": 8,
        "name": "discord",
        "type_info": "Varchar"
      },
      {
        "ordinal": 9,
        "name": "twitter",
        "type_info": "Varchar"
      },
      {
        "ordinal": 10,
        "name": "royalty",
        "type_info": "Numeric"
      },
      {
        "ordinal": 11,
        "name": "total_volume",
        "type_info": "Int8"
      },
      {
        "ordinal": 12,
        "name": "total_sale",
        "type_info": "Int8"
      },
      {
        "ordinal": 13,
        "name": "total_owner",
        "type_info": "Int8"
      },
      {
        "ordinal": 14,
        "name": "floor",
        "type_info": "Int8"
      },
      {
        "ordinal": 15,
        "name": "listed",
        "type_info": "Int8"
      }
    ],
    "parameters": {
      "Left": [
        "Text",
        "Text",
        "Int8",
        "Int8"
      ]
    },
    "nullable": [
      false,
      true,
      true,
      true,
      true,
      true,
      true,
      true,
      true,
      true,
      true,
      null,
      null,
      null,
      null,
      null
    ]
  },
  "hash": "de989c38d34b3a00c8bfa698dcc0f285a82790874d7ecb6084cf6879b9a86992"
}
